pqapi/__init__.py
pqapi/api.py
pqapi/models.py
pqapi/py.typed
pqapi/utils.py
pqapi/version.py
pqapi-7.4.0.dist-info/licenses/LICENSE
pqapi-7.4.0.dist-info/METADATA
pqapi-7.4.0.dist-info/WHEEL
pqapi-7.4.0.dist-info/top_level.txt
pqapi-7.4.0.dist-info/RECORD
