Metadata-Version: 2.4
Name: pqapi
Version: 7.4.0
Summary: API for interacting with paperqa.app
Author-email: Andrew White <andrew@futurehouse.org>
Maintainer-email: Andrew White <andrew@futurehouse.org>, James Braza <james@futurehouse.org>, Michael Skarlinski <mskarlinski@futurehouse.org>
License: MIT License
Project-URL: issues, https://github.com/Future-House/paperqa-api/issues
Project-URL: repository, https://github.com/Future-House/paperqa-api
Classifier: Intended Audience :: Developers
Classifier: License :: OSI Approved :: MIT License
Classifier: Operating System :: OS Independent
Classifier: Programming Language :: Python :: 3 :: Only
Classifier: Programming Language :: Python :: 3.11
Classifier: Programming Language :: Python :: 3.12
Classifier: Programming Language :: Python :: 3.13
Classifier: Programming Language :: Python
Classifier: Topic :: Software Development
Requires-Python: >=3.11.0rc1
License-File: LICENSE
Requires-Dist: aiohttp
Requires-Dist: fhaviary>=0.14.0
Requires-Dist: fhaviary[litqa]
Requires-Dist: paper-qa>=5.27.0
Requires-Dist: pydantic~=2.0
Requires-Dist: requests
Requires-Dist: tenacity
Provides-Extra: dev
Requires-Dist: click; extra == "dev"
Requires-Dist: ipython>=8; extra == "dev"
Requires-Dist: mypy>=1.8; extra == "dev"
Requires-Dist: pre-commit>=3.4; extra == "dev"
Requires-Dist: pylint-pydantic; extra == "dev"
Requires-Dist: pylint>=3.2; extra == "dev"
Requires-Dist: pytest; extra == "dev"
Requires-Dist: pytest-asyncio; extra == "dev"
Requires-Dist: pytest-cov>=5; extra == "dev"
Requires-Dist: pytest-sugar; extra == "dev"
Requires-Dist: pytest-timer[colorama]; extra == "dev"
Requires-Dist: pytest-xdist; extra == "dev"
Requires-Dist: refurb>=2; extra == "dev"
Requires-Dist: typeguard; extra == "dev"
Requires-Dist: types-requests; extra == "dev"
Dynamic: license-file
